pyproject.toml
rpkilog/__init__.py
rpkilog/archive_site_crawler.py
rpkilog/hapi.py
rpkilog/ingest_tar.py
rpkilog/routinator_snapshot_file.py
rpkilog/routinator_vrp_fetcher.py
rpkilog/vrp_diff.py
rpkilog.egg-info/PKG-INFO
rpkilog.egg-info/SOURCES.txt
rpkilog.egg-info/dependency_links.txt
rpkilog.egg-info/entry_points.txt
rpkilog.egg-info/requires.txt
rpkilog.egg-info/top_level.txt